[
  {
    "id": "1",
    "title": "Pressure cooker refried beans",
    "difficulty": "Easy",
    "image": "https://apipics.s3.amazonaws.com/mexican_api/1.jpg"
  },
  {
    "id": "2",
    "title": "Black bean chilli soup with corn dumplings",
    "difficulty": "Easy",
    "image": "https://apipics.s3.amazonaws.com/mexican_api/2.jpg"
  },
  {
    "id": "3",
    "title": "Fishcake tacos",
    "difficulty": "Easy",
    "image": "https://apipics.s3.amazonaws.com/mexican_api/3.jpg"
  },
  {
    "id": "4",
    "title": "Black bean and chicken burritos",
    "difficulty": "Easy",
    "image": "https://apipics.s3.amazonaws.com/mexican_api/4.jpg"
  },
  {
    "id": "5",
    "title": "Pork tacos with sweetcorn and feta",
    "difficulty": "Easy",
    "image": "https://apipics.s3.amazonaws.com/mexican_api/5.jpg"
  },
  {
    "id": "6",
    "title": "Taco slaw with pink pickled onions",
    "difficulty": "Easy",
    "image": "https://apipics.s3.amazonaws.com/mexican_api/6.jpg"
  },
  {
    "id": "7",
    "title": "Smoky chipotle tofu with tomatoes and avocado",
    "difficulty": "Easy",
    "image": "https://apipics.s3.amazonaws.com/mexican_api/7.jpg"
  },
  {
    "id": "8",
    "title": "Chilaquiles with fresh tomatillo salsa",
    "difficulty": "Medium",
    "image": "https://apipics.s3.amazonaws.com/mexican_api/8.jpg"
  },
  {
    "id": "9",
    "title": "Chipotle baked eggs",
    "difficulty": "Easy",
    "image": "https://apipics.s3.amazonaws.com/mexican_api/9.jpg"
  },
  {
    "id": "10",
    "title": "Venison tacos with grilled spring onions and peanut salsa",
    "difficulty": "Easy",
    "image": "https://apipics.s3.amazonaws.com/mexican_api/10.jpg"
  },
  {
    "id": "11",
    "title": "Easy huevos rancheros",
    "difficulty": "Medium",
    "image": "https://apipics.s3.amazonaws.com/mexican_api/11.jpg"
  },
  {
    "id": "12",
    "title": "Turkey pozole",
    "difficulty": "Easy",
    "image": "https://apipics.s3.amazonaws.com/mexican_api/12.jpg"
  },
  {
    "id": "13",
    "title": "Mexican-style barbecued beef brisket with quick-pickled onions",
    "difficulty": "Medium",
    "image": "https://apipics.s3.amazonaws.com/mexican_api/13.jpg"
  },
  {
    "id": "14",
    "title": "Frozen mango margarita",
    "difficulty": "Easy",
    "image": "https://apipics.s3.amazonaws.com/mexican_api/14.jpg"
  },
  {
    "id": "15",
    "title": "Raspberry margarita",
    "difficulty": "Easy",
    "image": "https://apipics.s3.amazonaws.com/mexican_api/15.jpg"
  },
  {
    "id": "16",
    "title": "Enchiladas verdes",
    "difficulty": "Easy",
    "image": "https://apipics.s3.amazonaws.com/mexican_api/16.jpg"
  },
  {
    "id": "17",
    "title": "Margarita cheesecake with tequila strawberries",
    "difficulty": "Easy",
    "image": "https://apipics.s3.amazonaws.com/mexican_api/17.jpg"
  },
  {
    "id": "18",
    "title": "Bolognese quesadilla",
    "difficulty": "Easy",
    "image": "https://apipics.s3.amazonaws.com/mexican_api/18.jpg"
  },
  {
    "id": "19",
    "title": "Sausage burritos with pea and avocado guacamole",
    "difficulty": "Easy",
    "image": "https://apipics.s3.amazonaws.com/mexican_api/19.jpg"
  },
  {
    "id": "20",
    "title": "Taco traybake",
    "difficulty": "Easy",
    "image": "https://apipics.s3.amazonaws.com/mexican_api/20.jpg"
  },
  {
    "id": "21",
    "title": "Slow-cooked chipotle chicken",
    "difficulty": "Easy",
    "image": "https://apipics.s3.amazonaws.com/mexican_api/21.jpg"
  },
  {
    "id": "22",
    "title": "Beef burrito bowls",
    "difficulty": "Easy",
    "image": "https://apipics.s3.amazonaws.com/mexican_api/22.jpg"
  },
  {
    "id": "23",
    "title": "Classic margarita cocktail",
    "difficulty": "Easy",
    "image": "https://apipics.s3.amazonaws.com/mexican_api/23.jpg"
  },
  {
    "id": "24",
    "title": "Ensenada fish tacos",
    "difficulty": "Easy",
    "image": "https://apipics.s3.amazonaws.com/mexican_api/24.jpg"
  },
  {
    "id": "25",
    "title": "Tex-Mex enchilada bake",
    "difficulty": "Easy",
    "image": "https://apipics.s3.amazonaws.com/mexican_api/25.jpg"
  },
  {
    "id": "26",
    "title": "Scampi tacos with jalapeño tartare sauce and avocado",
    "difficulty": "Easy",
    "image": "https://apipics.s3.amazonaws.com/mexican_api/26.jpg"
  },
  {
    "id": "27",
    "title": "Crispy tacos with charred veg and refried beans",
    "difficulty": "Easy",
    "image": "https://apipics.s3.amazonaws.com/mexican_api/27.jpg"
  },
  {
    "id": "28",
    "title": "Slow-cooked chicken tinga tacos with pickled onions",
    "difficulty": "Medium",
    "image": "https://apipics.s3.amazonaws.com/mexican_api/28.jpg"
  },
  {
    "id": "29",
    "title": "Mexican chicken and red rice burrito bowls",
    "difficulty": "Easy",
    "image": "https://apipics.s3.amazonaws.com/mexican_api/29.jpg"
  },
  {
    "id": "30",
    "title": "Cornbread with Mexican-style salad",
    "difficulty": "Easy",
    "image": "https://apipics.s3.amazonaws.com/mexican_api/30.jpg"
  },
  {
    "id": "31",
    "title": "Sweet potato and black bean nachos",
    "difficulty": "Easy",
    "image": "https://apipics.s3.amazonaws.com/mexican_api/31.jpg"
  },
  {
    "id": "32",
    "title": "Za’atar-spiced lamb tacos",
    "difficulty": "Easy",
    "image": "https://apipics.s3.amazonaws.com/mexican_api/32.jpg"
  },
  {
    "id": "33",
    "title": "Perfect guacamole",
    "difficulty": "Easy",
    "image": "https://apipics.s3.amazonaws.com/mexican_api/33.jpg"
  },
  {
    "id": "34",
    "title": "Steak and pepper fajitas",
    "difficulty": "Easy",
    "image": "https://apipics.s3.amazonaws.com/mexican_api/34.jpg"
  },
  {
    "id": "35",
    "title": "Jalapeño, bacon and crispy potato frittata",
    "difficulty": "Easy",
    "image": "https://apipics.s3.amazonaws.com/mexican_api/35.jpg"
  },
  {
    "id": "36",
    "title": "Paloma cocktail",
    "difficulty": "Easy",
    "image": "https://apipics.s3.amazonaws.com/mexican_api/36.jpg"
  },
  {
    "id": "37",
    "title": "Mexican-style prawn rice with avocado salsa",
    "difficulty": "Easy",
    "image": "https://apipics.s3.amazonaws.com/mexican_api/37.jpg"
  },
  {
    "id": "38",
    "title": "Fish and chip tacos with pea guacamole",
    "difficulty": "Medium",
    "image": "https://apipics.s3.amazonaws.com/mexican_api/38.jpg"
  },
  {
    "id": "39",
    "title": "Sweet potato, pea and cheese quesadillas",
    "difficulty": "Easy",
    "image": "https://apipics.s3.amazonaws.com/mexican_api/39.jpg"
  },
  {
    "id": "40",
    "title": "Taco salad bowls with prawns",
    "difficulty": "Easy",
    "image": "https://apipics.s3.amazonaws.com/mexican_api/40.jpg"
  },
  {
    "id": "41",
    "title": "Chicken and pepper pie with tortilla crisps",
    "difficulty": "Easy",
    "image": "https://apipics.s3.amazonaws.com/mexican_api/41.jpg"
  },
  {
    "id": "42",
    "title": "Mexican-style pork carnitas",
    "difficulty": "Easy",
    "image": "https://apipics.s3.amazonaws.com/mexican_api/42.jpg"
  },
  {
    "id": "43",
    "title": "Sweet potato chilli nachos",
    "difficulty": "Easy",
    "image": "https://apipics.s3.amazonaws.com/mexican_api/43.jpg"
  },
  {
    "id": "44",
    "title": "Easy Mexican chicken traybake",
    "difficulty": "Easy",
    "image": "https://apipics.s3.amazonaws.com/mexican_api/44.jpg"
  },
  {
    "id": "45",
    "title": "Sweet potato, red pepper and turkey enchiladas",
    "difficulty": "Easy",
    "image": "https://apipics.s3.amazonaws.com/mexican_api/45.jpg"
  },
  {
    "id": "46",
    "title": "Breakfast burrito",
    "difficulty": "Easy",
    "image": "https://apipics.s3.amazonaws.com/mexican_api/46.jpg"
  },
  {
    "id": "47",
    "title": "Mexican chicken and tortilla stew",
    "difficulty": "Easy",
    "image": "https://apipics.s3.amazonaws.com/mexican_api/47.jpg"
  },
  {
    "id": "48",
    "title": "Black bean, sweetcorn and red pepper chimichangas",
    "difficulty": "Easy",
    "image": "https://apipics.s3.amazonaws.com/mexican_api/48.jpg"
  },
  {
    "id": "49",
    "title": "Real black bean chilli con carne with avocado and lime salsa",
    "difficulty": "Easy",
    "image": "https://apipics.s3.amazonaws.com/mexican_api/49.jpg"
  },
  {
    "id": "50",
    "title": "Cheesy quesadillas with tomato, red pepper and avocado salsa",
    "difficulty": "Easy",
    "image": "https://apipics.s3.amazonaws.com/mexican_api/50.jpg"
  },
  {
    "id": "51",
    "title": "Prawn tacos",
    "difficulty": "Easy",
    "image": "https://apipics.s3.amazonaws.com/mexican_api/51.jpg"
  },
  {
    "id": "52",
    "title": "Mexican chicken taco salad",
    "difficulty": "Easy",
    "image": "https://apipics.s3.amazonaws.com/mexican_api/52.jpg"
  },
  {
    "id": "53",
    "title": "Nachos with pulled pork and sweetcorn salsa",
    "difficulty": "Medium",
    "image": "https://apipics.s3.amazonaws.com/mexican_api/53.jpg"
  },
  {
    "id": "54",
    "title": "Crispy Mexican tortilla rice bowl",
    "difficulty": "Easy",
    "image": "https://apipics.s3.amazonaws.com/mexican_api/54.jpg"
  },
  {
    "id": "55",
    "title": "Charred corn and chicken tacos",
    "difficulty": "Easy",
    "image": "https://apipics.s3.amazonaws.com/mexican_api/55.jpg"
  },
  {
    "id": "56",
    "title": "Mexican chicken burgers",
    "difficulty": "Easy",
    "image": "https://apipics.s3.amazonaws.com/mexican_api/56.jpg"
  },
  {
    "id": "57",
    "title": "Mexican fish tacos",
    "difficulty": "Easy",
    "image": "https://apipics.s3.amazonaws.com/mexican_api/57.jpg"
  },
  {
    "id": "58",
    "title": "Brazilian black bean soup with raw corn salsa",
    "difficulty": "Easy",
    "image": "https://apipics.s3.amazonaws.com/mexican_api/58.jpg"
  },
  {
    "id": "59",
    "title": "Cornbread with deep-fried crispy onions",
    "difficulty": "Easy",
    "image": "https://apipics.s3.amazonaws.com/mexican_api/59.jpg"
  },
  {
    "id": "60",
    "title": "Corned beef and bean hash with chimichurri",
    "difficulty": "Easy",
    "image": "https://apipics.s3.amazonaws.com/mexican_api/60.jpg"
  },
  {
    "id": "61",
    "title": "Slow-cooked duck tacos with pineapple salsa",
    "difficulty": "Medium",
    "image": "https://apipics.s3.amazonaws.com/mexican_api/61.jpg"
  },
  {
    "id": "62",
    "title": "Mexican picadillo pasties",
    "difficulty": "Easy",
    "image": "https://apipics.s3.amazonaws.com/mexican_api/62.jpg"
  },
  {
    "id": "63",
    "title": "Smoky pork and black bean stew with kale",
    "difficulty": "Easy",
    "image": "https://apipics.s3.amazonaws.com/mexican_api/63.jpg"
  },
  {
    "id": "64",
    "title": "Mexican veggie and tortilla soup",
    "difficulty": "Easy",
    "image": "https://apipics.s3.amazonaws.com/mexican_api/64.jpg"
  },
  {
    "id": "65",
    "title": "Smoky sausage chilli",
    "difficulty": "Easy",
    "image": "https://apipics.s3.amazonaws.com/mexican_api/65.jpg"
  },
  {
    "id": "66",
    "title": "Vegan chilli with rice",
    "difficulty": "Easy",
    "image": "https://apipics.s3.amazonaws.com/mexican_api/66.jpg"
  },
  {
    "id": "67",
    "title": "Easy shakshuka",
    "difficulty": "Easy",
    "image": "https://apipics.s3.amazonaws.com/mexican_api/67.jpg"
  },
  {
    "id": "68",
    "title": "Spicy ancho chilli, chicken and chorizo hotpot",
    "difficulty": "Easy",
    "image": "https://apipics.s3.amazonaws.com/mexican_api/68.jpg"
  },
  {
    "id": "69",
    "title": "Harissa-spiced lamb tacos",
    "difficulty": "Easy",
    "image": "https://apipics.s3.amazonaws.com/mexican_api/69.jpg"
  },
  {
    "id": "70",
    "title": "Smoked-lentil tacos with pico de gallo",
    "difficulty": "Medium",
    "image": "https://apipics.s3.amazonaws.com/mexican_api/70.jpg"
  },
  {
    "id": "71",
    "title": "Green veg and chicken tacos with pea guacamole",
    "difficulty": "Easy",
    "image": "https://apipics.s3.amazonaws.com/mexican_api/71.jpg"
  },
  {
    "id": "72",
    "title": "Smoky bean and sweet potato tortillas with lime-pickled onions",
    "difficulty": "Easy",
    "image": "https://apipics.s3.amazonaws.com/mexican_api/72.jpg"
  },
  {
    "id": "73",
    "title": "Smoky coriander beef fajitas",
    "difficulty": "Easy",
    "image": "https://apipics.s3.amazonaws.com/mexican_api/73.jpg"
  },
  {
    "id": "74",
    "title": "Chipotle chicken chilli with avocado",
    "difficulty": "Easy",
    "image": "https://apipics.s3.amazonaws.com/mexican_api/74.jpg"
  },
  {
    "id": "75",
    "title": "Braised beef chilli",
    "difficulty": "Easy",
    "image": "https://apipics.s3.amazonaws.com/mexican_api/75.jpg"
  },
  {
    "id": "76",
    "title": "Veggie chilli with nachos",
    "difficulty": "Easy",
    "image": "https://apipics.s3.amazonaws.com/mexican_api/76.jpg"
  },
  {
    "id": "77",
    "title": "Red pepper and courgette enchiladas",
    "difficulty": "Easy",
    "image": "https://apipics.s3.amazonaws.com/mexican_api/77.jpg"
  },
  {
    "id": "78",
    "title": "Beef enchiladas",
    "difficulty": "Easy",
    "image": "https://apipics.s3.amazonaws.com/mexican_api/78.jpg"
  },
  {
    "id": "79",
    "title": "Fried kale with black bean chilli and guacamole",
    "difficulty": "Easy",
    "image": "https://apipics.s3.amazonaws.com/mexican_api/79.jpg"
  },
  {
    "id": "80",
    "title": "Spicy turkey enchiladas",
    "difficulty": "Easy",
    "image": "https://apipics.s3.amazonaws.com/mexican_api/80.jpg"
  },
  {
    "id": "81",
    "title": "Cheddar, jalapeño, chilli and sweetcorn muffins",
    "difficulty": "Easy",
    "image": "https://apipics.s3.amazonaws.com/mexican_api/81.jpg"
  },
  {
    "id": "82",
    "title": "Parmesan taco shells",
    "difficulty": "Easy",
    "image": "https://apipics.s3.amazonaws.com/mexican_api/82.jpg"
  },
  {
    "id": "83",
    "title": "Beef fajitas with avocado and sweetcorn salsa",
    "difficulty": "Easy",
    "image": "https://apipics.s3.amazonaws.com/mexican_api/83.jpg"
  },
  {
    "id": "84",
    "title": "Vegetarian huevos rancheros",
    "difficulty": "Easy",
    "image": "https://apipics.s3.amazonaws.com/mexican_api/84.jpg"
  },
  {
    "id": "85",
    "title": "Lighter chicken enchiladas",
    "difficulty": "Easy",
    "image": "https://apipics.s3.amazonaws.com/mexican_api/85.jpg"
  },
  {
    "id": "86",
    "title": "Smoky sweetcorn fritters with tarragon yogurt",
    "difficulty": "Easy",
    "image": "https://apipics.s3.amazonaws.com/mexican_api/86.jpg"
  },
  {
    "id": "87",
    "title": "Ultimate chilli",
    "difficulty": "Easy",
    "image": "https://apipics.s3.amazonaws.com/mexican_api/87.jpg"
  },
  {
    "id": "88",
    "title": "Spicy guacamole",
    "difficulty": "Easy",
    "image": "https://apipics.s3.amazonaws.com/mexican_api/88.jpg"
  },
  {
    "id": "89",
    "title": "Tomato salsa salad",
    "difficulty": "Easy",
    "image": "https://apipics.s3.amazonaws.com/mexican_api/89.jpg"
  },
  {
    "id": "90",
    "title": "Spicy Mexican tortilla soup with avocado salsa",
    "difficulty": "Easy",
    "image": "https://apipics.s3.amazonaws.com/mexican_api/90.jpg"
  },
  {
    "id": "91",
    "title": "Quick chilli con carne",
    "difficulty": "Easy",
    "image": "https://apipics.s3.amazonaws.com/mexican_api/91.jpg"
  },
  {
    "id": "92",
    "title": "Tres leches cake with white russian syrup",
    "difficulty": "Medium",
    "image": "https://apipics.s3.amazonaws.com/mexican_api/92.jpg"
  },
  {
    "id": "93",
    "title": "Ernesto’s winning chilli",
    "difficulty": "Easy",
    "image": "https://apipics.s3.amazonaws.com/mexican_api/93.jpg"
  },
  {
    "id": "94",
    "title": "Beef chilli with dark chocolate",
    "difficulty": "Easy",
    "image": "https://apipics.s3.amazonaws.com/mexican_api/94.jpg"
  },
  {
    "id": "95",
    "title": "Smoky beef chilli with black beans",
    "difficulty": "Easy",
    "image": "https://apipics.s3.amazonaws.com/mexican_api/95.jpg"
  },
  {
    "id": "96",
    "title": "Drunken caterpillar chilli con carne",
    "difficulty": "Medium",
    "image": "https://apipics.s3.amazonaws.com/mexican_api/96.jpg"
  },
  {
    "id": "97",
    "title": "Barbecue sweet potatoes with garlic and herb dressing",
    "difficulty": "Easy",
    "image": "https://apipics.s3.amazonaws.com/mexican_api/97.jpg"
  },
  {
    "id": "98",
    "title": "Griddled cheesy cornbreads",
    "difficulty": "Easy",
    "image": "https://apipics.s3.amazonaws.com/mexican_api/98.jpg"
  },
  {
    "id": "99",
    "title": "Leftover chicken quesadillas",
    "difficulty": "Easy",
    "image": "https://apipics.s3.amazonaws.com/mexican_api/99.jpg"
  },
  {
    "id": "100",
    "title": "Sweetcorn salsa",
    "difficulty": "Easy",
    "image": "https://apipics.s3.amazonaws.com/mexican_api/100.jpg"
  },
  {
    "id": "101",
    "title": "Mexican lamb wraps with guacamole",
    "difficulty": "Easy",
    "image": "https://apipics.s3.amazonaws.com/mexican_api/101.jpg"
  },
  {
    "id": "102",
    "title": "Mexican mole rojo",
    "difficulty": "Easy",
    "image": "https://apipics.s3.amazonaws.com/mexican_api/102.jpg"
  },
  {
    "id": "103",
    "title": "Diana Henry’s Mexican chicken and pumpkin with pepita pesto",
    "difficulty": "Easy",
    "image": "https://apipics.s3.amazonaws.com/mexican_api/103.jpg"
  },
  {
    "id": "104",
    "title": "Vegetarian chilli",
    "difficulty": "Easy",
    "image": "https://apipics.s3.amazonaws.com/mexican_api/104.jpg"
  },
  {
    "id": "105",
    "title": "One-pan chilli eggs with guacamole",
    "difficulty": "Easy",
    "image": "https://apipics.s3.amazonaws.com/mexican_api/105.jpg"
  },
  {
    "id": "106",
    "title": "Quick steak fajitas with pickled red onions",
    "difficulty": "Easy",
    "image": "https://apipics.s3.amazonaws.com/mexican_api/106.jpg"
  },
  {
    "id": "107",
    "title": "Mexican baked beans",
    "difficulty": "Easy",
    "image": "https://apipics.s3.amazonaws.com/mexican_api/107.jpg"
  },
  {
    "id": "108",
    "title": "Chilli con carne with avocado and chilli salsa",
    "difficulty": "Easy",
    "image": "https://apipics.s3.amazonaws.com/mexican_api/108.jpg"
  },
  {
    "id": "109",
    "title": "Maple and chilli pork wraps with smoky mayo",
    "difficulty": "Easy",
    "image": "https://apipics.s3.amazonaws.com/mexican_api/109.jpg"
  },
  {
    "id": "110",
    "title": "Mojito tin-can cupcakes",
    "difficulty": "Easy",
    "image": "https://apipics.s3.amazonaws.com/mexican_api/110.jpg"
  },
  {
    "id": "111",
    "title": "Nachos with oxtail chilli",
    "difficulty": "Easy",
    "image": "https://apipics.s3.amazonaws.com/mexican_api/111.jpg"
  },
  {
    "id": "112",
    "title": "Chicken fajitas with corn salsa",
    "difficulty": "Easy",
    "image": "https://apipics.s3.amazonaws.com/mexican_api/112.jpg"
  },
  {
    "id": "113",
    "title": "Chunky chilli chicken soup",
    "difficulty": "Easy",
    "image": "https://apipics.s3.amazonaws.com/mexican_api/113.jpg"
  },
  {
    "id": "114",
    "title": "Mexican-style pork wraps",
    "difficulty": "Easy",
    "image": "https://apipics.s3.amazonaws.com/mexican_api/114.jpg"
  },
  {
    "id": "115",
    "title": "Tex-Mex beef burritos",
    "difficulty": "Easy",
    "image": "https://apipics.s3.amazonaws.com/mexican_api/115.jpg"
  },
  {
    "id": "116",
    "title": "Chipotle black bean chilli with guacamole",
    "difficulty": "Easy",
    "image": "https://apipics.s3.amazonaws.com/mexican_api/116.jpg"
  },
  {
    "id": "117",
    "title": "Smokin’ hot cocktail",
    "difficulty": "Easy",
    "image": "https://apipics.s3.amazonaws.com/mexican_api/117.jpg"
  },
  {
    "id": "118",
    "title": "Black bean burger with seared halloumi",
    "difficulty": "Easy",
    "image": "https://apipics.s3.amazonaws.com/mexican_api/118.jpg"
  },
  {
    "id": "119",
    "title": "Spiced sweetcorn and potato fritters with guacamole",
    "difficulty": "Easy",
    "image": "https://apipics.s3.amazonaws.com/mexican_api/119.jpg"
  },
  {
    "id": "120",
    "title": "Beef nachos",
    "difficulty": "Easy",
    "image": "https://apipics.s3.amazonaws.com/mexican_api/120.jpg"
  }
]
